examples/verilog_optimization/initial_program.v
module popcount16 (
    input [15:0] in,
    output reg [4:0] out
);

  always @(*) begin
    // Initial dummy implementation: always returns 0
    // The goal is to evolve this into a correct population count function
    out = 5'b0;
  end

endmodule

examples/verilog_optimization/testbench.v
`timescale 1ns / 1ps

module testbench;

  reg [15:0] in;
  wire [4:0] out;
  
  // Instantiate the Unit Under Test (UUT)
  popcount16 uut (
    .in(in), 
    .out(out)
  );

  integer i;
  integer correct_count;
  integer total_tests;
  reg [4:0] expected;
  integer j;

  // Function to calculate expected popcount
  function [4:0] calc_popcount;
    input [15:0] val;
    integer k;
    begin
      calc_popcount = 0;
      for (k = 0; k < 16; k = k + 1) begin
        if (val[k]) calc_popcount = calc_popcount + 1;
      end
    end
  endfunction

  initial begin
    $dumpfile("waveform.vcd");
    $dumpvars(0, testbench);

    correct_count = 0;
    total_tests = 100;

    // Test specific cases
    in = 16'h0000; #10;
    expected = calc_popcount(in);
    check_result();

    in = 16'hFFFF; #10;
    expected = calc_popcount(in);
    check_result();

    in = 16'hAAAA; #10;
    expected = calc_popcount(in);
    check_result();

    in = 16'h5555; #10;
    expected = calc_popcount(in);
    check_result();

    // Random tests
    for (i = 0; i < total_tests - 4; i = i + 1) begin
      in = $random;
      #10;
      expected = calc_popcount(in);
      check_result();
    end

    // Print final summary for evaluator parsing
    $display("SUMMARY: Passed %0d/%0d tests", correct_count, total_tests);
    
    if (correct_count == total_tests)
      $display("RESULT: PASS");
    else
      $display("RESULT: FAIL");

    $finish;
  end

  task check_result;
    begin
      if (out === expected) begin
        correct_count = correct_count + 1;
      end else begin
        $display("ERROR: in=%h, out=%d, expected=%d", in, out, expected);
      end
    end
  endtask

endmodule

waveform.vcd
$date
	Sat Jan 17 20:39:56 2026
$end
$version
	Icarus Verilog
$end
$timescale
	1ps
$end
$scope module testbench $end
$var wire 5 ! out [4:0] $end
$var reg 5 " expected [4:0] $end
$var reg 16 # in [15:0] $end
$var integer 32 $ correct_count [31:0] $end
$var integer 32 % i [31:0] $end
$var integer 32 & total_tests [31:0] $end
$scope function calc_popcount $end
$var reg 16 ' val [15:0] $end
$var integer 32 ( k [31:0] $end
$upscope $end
$scope module uut $end
$var wire 16 ) in [15:0] $end
$var reg 5 * out [4:0] $end
$upscope $end
$scope task check_result $end
$upscope $end
$upscope $end
$enddefinitions $end
$comment Show the parameter values. $end
$dumpall
$end
#0
$dumpvars
b0 *
b0 )
bx (
bx '
b1100100 &
bx %
b0 $
b0 #
bx "
b0 !
$end
#10000
b10000 !
b10000 *
b1111111111111111 #
b1111111111111111 )
b1 $
b0 "
b10000 (
b0 '
#20000
b1000 !
b1000 *
b1010101010101010 #
b1010101010101010 )
b10 $
b10000 "
b10000 (
b1111111111111111 '
#30000
b1000 !
b1000 *
b101010101010101 #
b101010101010101 )
b11 $
b1000 "
b10000 (
b1010101010101010 '
#40000
b110 !
b110 *
b11010100100100 #
b11010100100100 )
b0 %
b100 $
b10000 (
b101010101010101 '
#50000
b111 !
b111 *
b101111010000001 #
b101111010000001 )
b1 %
b101 $
b110 "
b10000 (
b11010100100100 '
#60000
b111 !
b111 *
b1101011000001001 #
b1101011000001001 )
b10 %
b110 $
b111 "
b10000 (
b101111010000001 '
#70000
b1000 !
b1000 *
b101011001100011 #
b101011001100011 )
b11 %
b111 $
b10000 (
b1101011000001001 '
#80000
b1001 !
b1001 *
b111101100001101 #
b111101100001101 )
b100 %
b1000 $
b1000 "
b10000 (
b101011001100011 '
#90000
b1000 !
b1000 *
b1001100110001101 #
b1001100110001101 )
b101 %
b1001 $
b1001 "
b10000 (
b111101100001101 '
#100000
b110 !
b110 *
b1000010001100101 #
b1000010001100101 )
b110 %
b1010 $
b1000 "
b10000 (
b1001100110001101 '
#110000
b101 !
b101 *
b101001000010010 #
b101001000010010 )
b111 %
b1011 $
b110 "
b10000 (
b1000010001100101 '
#120000
b110 !
b110 *
b1110001100000001 #
b1110001100000001 )
b1000 %
b1100 $
b101 "
b10000 (
b101001000010010 '
#130000
b1000 !
b1000 *
b1100110100001101 #
b1100110100001101 )
b1001 %
b1101 $
b110 "
b10000 (
b1110001100000001 '
#140000
b1010 !
b1010 *
b1111000101110110 #
b1111000101110110 )
b1010 %
b1110 $
b1000 "
b10000 (
b1100110100001101 '
#150000
b1010 !
b1010 *
b1100110100111101 #
b1100110100111101 )
b1011 %
b1111 $
b1010 "
b10000 (
b1111000101110110 '
#160000
b1011 !
b1011 *
b101011111101101 #
b101011111101101 )
b1100 %
b10000 $
b10000 (
b1100110100111101 '
#170000
b1010 !
b1010 *
b1111011110001100 #
b1111011110001100 )
b1101 %
b10001 $
b1011 "
b10000 (
b101011111101101 '
#180000
b1011 !
b1011 *
b1110100111111001 #
b1110100111111001 )
b1110 %
b10010 $
b1010 "
b10000 (
b1111011110001100 '
#190000
b110 !
b110 *
b10010011000110 #
b10010011000110 )
b1111 %
b10011 $
b1011 "
b10000 (
b1110100111111001 '
#200000
b110 !
b110 *
b1000010011000101 #
b1000010011000101 )
b10000 %
b10100 $
b110 "
b10000 (
b10010011000110 '
#210000
b1000 !
b1000 *
b1101001010101010 #
b1101001010101010 )
b10001 %
b10101 $
b10000 (
b1000010011000101 '
#220000
b1100 !
b1100 *
b1111011111100101 #
b1111011111100101 )
b10010 %
b10110 $
b1000 "
b10000 (
b1101001010101010 '
#230000
b1010 !
b1010 *
b111001001110111 #
b111001001110111 )
b10011 %
b10111 $
b1100 "
b10000 (
b1111011111100101 '
#240000
b111 !
b111 *
b1101011000010010 #
b1101011000010010 )
b10100 %
b11000 $
b1010 "
b10000 (
b111001001110111 '
#250000
b1011 !
b1011 *
b1101101110001111 #
b1101101110001111 )
b10101 %
b11001 $
b111 "
b10000 (
b1101011000010010 '
#260000
b1001 !
b1001 *
b110100111110010 #
b110100111110010 )
b10110 %
b11010 $
b1011 "
b10000 (
b1101101110001111 '
#270000
b1001 !
b1001 *
b1001011011001110 #
b1001011011001110 )
b10111 %
b11011 $
b1001 "
b10000 (
b110100111110010 '
#280000
b1001 !
b1001 *
b111101011101000 #
b111101011101000 )
b11000 %
b11100 $
b10000 (
b1001011011001110 '
#290000
b1000 !
b1000 *
b100111011000101 #
b100111011000101 )
b11001 %
b11101 $
b10000 (
b111101011101000 '
#300000
b111 !
b111 *
b100100101011100 #
b100100101011100 )
b11010 %
b11110 $
b1000 "
b10000 (
b100111011000101 '
#310000
b1000 !
b1000 *
b10100010111101 #
b10100010111101 )
b11011 %
b11111 $
b111 "
b10000 (
b100100101011100 '
#320000
b111 !
b111 *
b101100000101101 #
b101100000101101 )
b11100 %
b100000 $
b1000 "
b10000 (
b10100010111101 '
#330000
b111 !
b111 *
b10011001100101 #
b10011001100101 )
b11101 %
b100001 $
b111 "
b10000 (
b101100000101101 '
#340000
b111 !
b111 *
b110001001100011 #
b110001001100011 )
b11110 %
b100010 $
b10000 (
b10011001100101 '
#350000
b110 !
b110 *
b1000011100001010 #
b1000011100001010 )
b11111 %
b100011 $
b10000 (
b110001001100011 '
#360000
b11 !
b11 *
b10001010000000 #
b10001010000000 )
b100000 %
b100100 $
b110 "
b10000 (
b1000011100001010 '
#370000
b11 !
b11 *
b10000100100000 #
b10000100100000 )
b100001 %
b100101 $
b11 "
b10000 (
b10001010000000 '
#380000
b111 !
b111 *
b100010110101010 #
b100010110101010 )
b100010 %
b100110 $
b10000 (
b10000100100000 '
#390000
b1001 !
b1001 *
b1100110010011101 #
b1100110010011101 )
b100011 %
b100111 $
b111 "
b10000 (
b100010110101010 '
#400000
b1001 !
b1001 *
b11111010010110 #
b11111010010110 )
b100100 %
b101000 $
b1001 "
b10000 (
b1100110010011101 '
#410000
b111 !
b111 *
b1011100000010011 #
b1011100000010011 )
b100101 %
b101001 $
b10000 (
b11111010010110 '
#420000
b110 !
b110 *
b11100000001101 #
b11100000001101 )
b100110 %
b101010 $
b111 "
b10000 (
b1011100000010011 '
#430000
b1001 !
b1001 *
b1101011001010011 #
b1101011001010011 )
b100111 %
b101011 $
b110 "
b10000 (
b11100000001101 '
#440000
b1011 !
b1011 *
b1101110101101011 #
b1101110101101011 )
b101000 %
b101100 $
b1001 "
b10000 (
b1101011001010011 '
#450000
b1000 !
b1000 *
b10101011010101 #
b10101011010101 )
b101001 %
b101101 $
b1011 "
b10000 (
b1101110101101011 '
#460000
b100 !
b100 *
b100101000000010 #
b100101000000010 )
b101010 %
b101110 $
b1000 "
b10000 (
b10101011010101 '
#470000
b1010 !
b1010 *
b11111010101110 #
b11111010101110 )
b101011 %
b101111 $
b100 "
b10000 (
b100101000000010 '
#480000
b1001 !
b1001 *
b1110100100011101 #
b1110100100011101 )
b101100 %
b110000 $
b1010 "
b10000 (
b11111010101110 '
#490000
b1010 !
b1010 *
b111001011001111 #
b111001011001111 )
b101101 %
b110001 $
b1001 "
b10000 (
b1110100100011101 '
#500000
b110 !
b110 *
b100100100100011 #
b100100100100011 )
b101110 %
b110010 $
b1010 "
b10000 (
b111001011001111 '
#510000
b110 !
b110 *
b110010100001010 #
b110010100001010 )
b101111 %
b110011 $
b110 "
b10000 (
b100100100100011 '
#520000
b110 !
b110 *
b101011001010 #
b101011001010 )
b110000 %
b110100 $
b10000 (
b110010100001010 '
#530000
b111 !
b111 *
b100110000111100 #
b100110000111100 )
b110001 %
b110101 $
b10000 (
b101011001010 '
#540000
b1011 !
b1011 *
b1011110111110010 #
b1011110111110010 )
b110010 %
b110110 $
b111 "
b10000 (
b100110000111100 '
#550000
b110 !
b110 *
b110000110001010 #
b110000110001010 )
b110011 %
b110111 $
b1011 "
b10000 (
b1011110111110010 '
#560000
b111 !
b111 *
b1011001101000001 #
b1011001101000001 )
b110100 %
b111000 $
b110 "
b10000 (
b110000110001010 '
#570000
b111 !
b111 *
b11010011011000 #
b11010011011000 )
b110101 %
b111001 $
b111 "
b10000 (
b1011001101000001 '
#580000
b1010 !
b1010 *
b1111001101111000 #
b1111001101111000 )
b110110 %
b111010 $
b10000 (
b11010011011000 '
#590000
b101 !
b101 *
b1001010001001 #
b1001010001001 )
b110111 %
b111011 $
b1010 "
b10000 (
b1111001101111000 '
#600000
b1001 !
b1001 *
b110111101011 #
b110111101011 )
b111000 %
b111100 $
b101 "
b10000 (
b1001010001001 '
#610000
b1001 !
b1001 *
b110010110110110 #
b110010110110110 )
b111001 %
b111101 $
b1001 "
b10000 (
b110111101011 '
#620000
b1010 !
b1010 *
b1111100111000110 #
b1111100111000110 )
b111010 %
b111110 $
b10000 (
b110010110110110 '
#630000
b1000 !
b1000 *
b1001110101110 #
b1001110101110 )
b111011 %
b111111 $
b1010 "
b10000 (
b1111100111000110 '
#640000
b110 !
b110 *
b1010111100 #
b1010111100 )
b111100 %
b1000000 $
b1000 "
b10000 (
b1001110101110 '
#650000
b1001 !
b1001 *
b1101110100101010 #
b1101110100101010 )
b111101 %
b1000001 $
b110 "
b10000 (
b1010111100 '
#660000
b111 !
b111 *
b1001101000001011 #
b1001101000001011 )
b111110 %
b1000010 $
b1001 "
b10000 (
b1101110100101010 '
#670000
b1010 !
b1010 *
b1011111001110001 #
b1011111001110001 )
b111111 %
b1000011 $
b111 "
b10000 (
b1001101000001011 '
#680000
b101 !
b101 *
b100000110000101 #
b100000110000101 )
b1000000 %
b1000100 $
b1010 "
b10000 (
b1011111001110001 '
#690000
b1001 !
b1001 *
b101010101001111 #
b101010101001111 )
b1000001 %
b1000101 $
b101 "
b10000 (
b100000110000101 '
#700000
b111 !
b111 *
b110000000111011 #
b110000000111011 )
b1000010 %
b1000110 $
b1001 "
b10000 (
b101010101001111 '
#710000
b1000 !
b1000 *
b11001100111010 #
b11001100111010 )
b1000011 %
b1000111 $
b111 "
b10000 (
b110000000111011 '
#720000
b1001 !
b1001 *
b11001001111110 #
b11001001111110 )
b1000100 %
b1001000 $
b1000 "
b10000 (
b11001100111010 '
#730000
b111 !
b111 *
b100101100010101 #
b100101100010101 )
b1000101 %
b1001001 $
b1001 "
b10000 (
b11001001111110 '
#740000
b1010 !
b1010 *
b1001101111110001 #
b1001101111110001 )
b1000110 %
b1001010 $
b111 "
b10000 (
b100101100010101 '
#750000
b1001 !
b1001 *
b100101111011001 #
b100101111011001 )
b1000111 %
b1001011 $
b1010 "
b10000 (
b1001101111110001 '
#760000
b110 !
b110 *
b11101100010 #
b11101100010 )
b1001000 %
b1001100 $
b1001 "
b10000 (
b100101111011001 '
#770000
b1010 !
b1010 *
b1111101101001100 #
b1111101101001100 )
b1001001 %
b1001101 $
b110 "
b10000 (
b11101100010 '
#780000
b1010 !
b1010 *
b101010110011111 #
b101010110011111 )
b1001010 %
b1001110 $
b1010 "
b10000 (
b1111101101001100 '
#790000
b1000 !
b1000 *
b1010000110001111 #
b1010000110001111 )
b1001011 %
b1001111 $
b10000 (
b101010110011111 '
#800000
b1001 !
b1001 *
b1010100111111000 #
b1010100111111000 )
b1001100 %
b1010000 $
b1000 "
b10000 (
b1010000110001111 '
#810000
b1000 !
b1000 *
b110000010110111 #
b110000010110111 )
b1001101 %
b1010001 $
b1001 "
b10000 (
b1010100111111000 '
#820000
b1010 !
b1010 *
b101011010011111 #
b101011010011111 )
b1001110 %
b1010010 $
b1000 "
b10000 (
b110000010110111 '
#830000
b111 !
b111 *
b1001010001011100 #
b1001010001011100 )
b1001111 %
b1010011 $
b1010 "
b10000 (
b101011010011111 '
#840000
b111 !
b111 *
b1100000001011011 #
b1100000001011011 )
b1010000 %
b1010100 $
b111 "
b10000 (
b1001010001011100 '
#850000
b1000 !
b1000 *
b11011110001001 #
b11011110001001 )
b1010001 %
b1010101 $
b10000 (
b1100000001011011 '
#860000
b110 !
b110 *
b11001001001001 #
b11001001001001 )
b1010010 %
b1010110 $
b1000 "
b10000 (
b11011110001001 '
#870000
b1000 !
b1000 *
b11111011010000 #
b11111011010000 )
b1010011 %
b1010111 $
b110 "
b10000 (
b11001001001001 '
#880000
b1000 !
b1000 *
b1100000011010111 #
b1100000011010111 )
b1010100 %
b1011000 $
b1000 "
b10000 (
b11111011010000 '
#890000
b1001 !
b1001 *
b1111110001010001 #
b1111110001010001 )
b1010101 %
b1011001 $
b10000 (
b1100000011010111 '
#900000
b1001 !
b1001 *
b10111110010110 #
b10111110010110 )
b1010110 %
b1011010 $
b1001 "
b10000 (
b1111110001010001 '
#910000
b1001 !
b1001 *
b111111100001100 #
b111111100001100 )
b1010111 %
b1011011 $
b10000 (
b10111110010110 '
#920000
b1000 !
b1000 *
b1100111011000010 #
b1100111011000010 )
b1011000 %
b1011100 $
b10000 (
b111111100001100 '
#930000
b1001 !
b1001 *
b1110110111001000 #
b1110110111001000 )
b1011001 %
b1011101 $
b1000 "
b10000 (
b1100111011000010 '
#940000
b1010 !
b1010 *
b101101001110111 #
b101101001110111 )
b1011010 %
b1011110 $
b1001 "
b10000 (
b1110110111001000 '
#950000
b1011 !
b1011 *
b1110110100111101 #
b1110110100111101 )
b1011011 %
b1011111 $
b1010 "
b10000 (
b101101001110111 '
#960000
b1000 !
b1000 *
b1101101100010010 #
b1101101100010010 )
b1011100 %
b1100000 $
b1011 "
b10000 (
b1110110100111101 '
#970000
b110 !
b110 *
b1111110 #
b1111110 )
b1011101 %
b1100001 $
b1000 "
b10000 (
b1101101100010010 '
#980000
b111 !
b111 *
b1000000101101101 #
b1000000101101101 )
b1011110 %
b1100010 $
b110 "
b10000 (
b1111110 '
#990000
b1010 !
b1010 *
b1110011100111001 #
b1110011100111001 )
b1011111 %
b1100011 $
b111 "
b10000 (
b1000000101101101 '
#1000000
b1100000 %
b1100100 $
b1010 "
b10000 (
b1110011100111001 '
